html4docx/__init__.py
html4docx/colors.py
html4docx/constants.py
html4docx/h4d.py
html4docx/metadata.py
html4docx/utils.py
html_for_docx-1.1.3.dist-info/licenses/LICENSE
tests/__init__.py
tests/conftest.py
tests/test_h4d.py
tests/test_metadata.py
html_for_docx-1.1.3.dist-info/METADATA
html_for_docx-1.1.3.dist-info/WHEEL
html_for_docx-1.1.3.dist-info/top_level.txt
html_for_docx-1.1.3.dist-info/RECORD
