Metadata-Version: 2.4
Name: html-for-docx
Version: 1.1.3
Summary: Convert HTML to Docx easily and fastly
Home-page: https://github.com/dfop02/html4docx
Download-URL: https://github.com/dfop02/html4docx/archive/1.1.3.tar.gz
Author: Diogo Fernandes
Author-email: diogofernandesop@gmail.com
Maintainer: Diogo Fernandes
Maintainer-email: diogofernandesop@gmail.com
License: MIT
Project-URL: Changelog, https://github.com/dfop02/html4docx/blob/master/HISTORY.rst
Project-URL: Bug Tracker, https://github.com/dfop02/html4docx/issues
Project-URL: Repository, https://github.com/dfop02/html4docx
Keywords: html,docx,docs,office,word,convert,transform
Platform: any
Classifier: Intended Audience :: Developers
Classifier: License :: OSI Approved :: MIT License
Classifier: Topic :: Software Development :: Build Tools
Classifier: Topic :: Software Development :: Libraries
Classifier: Topic :: Text Processing
Classifier: Topic :: Text Processing :: Markup :: HTML
Classifier: Topic :: Utilities
Classifier: Programming Language :: Python
Classifier: Programming Language :: Python :: 3
Classifier: Programming Language :: Python :: 3.7
Classifier: Programming Language :: Python :: 3.8
Classifier: Programming Language :: Python :: 3.9
Classifier: Programming Language :: Python :: 3.10
Classifier: Programming Language :: Python :: 3.11
Classifier: Programming Language :: Python :: 3.12
Classifier: Programming Language :: Python :: 3.13
Classifier: Programming Language :: Python :: 3.14
Requires-Python: >=3.7
License-File: LICENSE
Requires-Dist: python-docx>=1.1.0
Requires-Dist: beautifulsoup4>=4.12.2
Dynamic: author
Dynamic: author-email
Dynamic: classifier
Dynamic: description
Dynamic: download-url
Dynamic: home-page
Dynamic: keywords
Dynamic: license
Dynamic: license-file
Dynamic: platform
Dynamic: project-url
Dynamic: requires-dist
Dynamic: requires-python
Dynamic: summary
